basicApiModel/__init__.py
basicApiModel/app.py
basicApiModel/models/__init__.py
basicApiModel/models/project.py
basicApiModel/template/.dockerignore
basicApiModel/template/.env
basicApiModel/template/.gitattributes
basicApiModel/template/.gitignore
basicApiModel/template/Dockerfile
basicApiModel/template/requirements.txt
basicApiModel/template/your-project/app.py
basicApiModel/template/your-project/config.py
basicApiModel/template/your-project/log/log.py
basicApiModel/template/your-project/models/big_query.py
basicApiModel/template/your-project/models/payload.py
basicApiModel/template/your-project/models/response.py
basicApiModel/template/your-project/routes/route.py
basicApiModel/template/your-project/tools/date.py
basicapimodel-1.0.3.dist-info/METADATA
basicapimodel-1.0.3.dist-info/WHEEL
basicapimodel-1.0.3.dist-info/entry_points.txt
basicapimodel-1.0.3.dist-info/top_level.txt
basicapimodel-1.0.3.dist-info/RECORD
